api/README.md
api/__init__.py
api/api_server.py
api/api_wsgi.py
api/web.py
config/README.md
core/README.md
core/database.py
core/enhanced_search_engine.py
core/indexer.py
core/semantic_search.py
core/tree_parser.py
intelligent_codelens-1.0.6.dist-info/licenses/LICENSE
mcp/README.md
mcp/__init__.py
mcp/fastmcp_server.py
mcp/mcp_server.py
tools/README.md
tools/demo.py
intelligent_codelens-1.0.6.dist-info/METADATA
intelligent_codelens-1.0.6.dist-info/WHEEL
intelligent_codelens-1.0.6.dist-info/entry_points.txt
intelligent_codelens-1.0.6.dist-info/top_level.txt
intelligent_codelens-1.0.6.dist-info/RECORD
