Metadata-Version: 2.4
Name: intelligent-codelens
Version: 1.0.6
Summary: 智能代码搜索引擎，支持语义搜索和代码分析
Home-page: https://github.com/sokis/CodeLens
Author: CodeLens Team
Author-email: Your Name <your.email@example.com>
Maintainer: CodeLens Team
Maintainer-email: Your Name <your.email@example.com>
License: MIT
Project-URL: Homepage, https://github.com/sokis/CodeLens
Project-URL: Documentation, https://github.com/sokis/CodeLens/blob/main/README.md
Project-URL: Repository, https://github.com/sokis/CodeLens
Project-URL: Issues, https://github.com/sokis/CodeLens/issues
Keywords: codelens,code-search,semantic-search,ai,code-analysis
Platform: any
Classifier: Development Status :: 5 - Production/Stable
Classifier: Intended Audience :: Developers
Classifier: License :: OSI Approved :: MIT License
Classifier: Operating System :: OS Independent
Classifier: Programming Language :: Python :: 3
Classifier: Programming Language :: Python :: 3.8
Classifier: Programming Language :: Python :: 3.9
Classifier: Programming Language :: Python :: 3.10
Classifier: Programming Language :: Python :: 3.11
Classifier: Topic :: Software Development :: Libraries :: Python Modules
Classifier: Topic :: Text Processing :: Indexing
Classifier: Topic :: Scientific/Engineering :: Artificial Intelligence
Requires-Python: >=3.8
License-File: LICENSE
Requires-Dist: fastapi>=0.104.0
Requires-Dist: uvicorn[standard]>=0.24.0
Requires-Dist: sentence-transformers>=2.2.2
Requires-Dist: tree-sitter>=0.20.0
Requires-Dist: spacy>=3.7.0
Requires-Dist: numpy<2.0.0,>=1.24.0
Requires-Dist: pydantic>=2.0.0
Requires-Dist: python-multipart>=0.0.6
Requires-Dist: jinja2>=3.1.0
Requires-Dist: aiofiles>=23.0.0
Requires-Dist: httpx>=0.25.0
Requires-Dist: PyYAML>=6.0
Requires-Dist: scikit-learn>=1.3.0
Requires-Dist: jieba>=0.42.0
Provides-Extra: dev
Requires-Dist: pytest>=7.4.0; extra == "dev"
Requires-Dist: pytest-asyncio>=0.21.0; extra == "dev"
Requires-Dist: pytest-cov>=4.1.0; extra == "dev"
Requires-Dist: black>=23.0.0; extra == "dev"
Requires-Dist: isort>=5.12.0; extra == "dev"
Requires-Dist: mypy>=1.5.0; extra == "dev"
Requires-Dist: flake8>=6.0.0; extra == "dev"
Requires-Dist: pre-commit>=3.4.0; extra == "dev"
Provides-Extra: test
Requires-Dist: pytest>=7.4.0; extra == "test"
Requires-Dist: pytest-asyncio>=0.21.0; extra == "test"
Requires-Dist: pytest-cov>=4.1.0; extra == "test"
Requires-Dist: httpx>=0.25.0; extra == "test"
Dynamic: author
Dynamic: home-page
Dynamic: license-file
Dynamic: maintainer
Dynamic: platform
Dynamic: requires-python
